{"pid":8094,"direction":"Westbound","lengthFt":18842,"points":[{"seq":1,"lat":41.866215000001,"lon":-87.607628000002,"type":"S","stopId":"4877","stopName":"Solidarity Dr & Planetarium","pdist":0},{"seq":2,"lat":41.8662,"lon":-87.60763,"type":"W","pdist":0},{"seq":3,"lat":41.866236,"lon":-87.60742,"type":"W","pdist":0},{"seq":4,"lat":41.866499,"lon":-87.607439,"type":"W","pdist":0},{"seq":5,"lat":41.866504,"lon":-87.607473,"type":"W","pdist":0},{"seq":6,"lat":41.8665,"lon":-87.60792,"type":"W","pdist":0},{"seq":7,"lat":41.8665,"lon":-87.60833,"type":"W","pdist":0},{"seq":8,"lat":41.86649,"lon":-87.60865,"type":"W","pdist":0},{"seq":9,"lat":41.86649,"lon":-87.60913,"type":"W","pdist":0},{"seq":10,"lat":41.86647,"lon":-87.60992,"type":"W","pdist":0},{"seq":11,"lat":41.866498999999,"lon":-87.60992,"type":"S","stopId":"4593","stopName":"Solidarity Dr & Lynn White Drive","pdist":837},{"seq":12,"lat":41.86647,"lon":-87.60992,"type":"W","pdist":0},{"seq":13,"lat":41.86647,"lon":-87.61023,"type":"W","pdist":0},{"seq":14,"lat":41.86641,"lon":-87.61299,"type":"W","pdist":0},{"seq":15,"lat":41.866476,"lon":-87.612989999998,"type":"S","stopId":"4595","stopName":"Solidarity Drive & Aquarium","pdist":1695},{"seq":16,"lat":41.86641,"lon":-87.61299,"type":"W","pdist":0},{"seq":17,"lat":41.86641,"lon":-87.61321,"type":"W","pdist":0},{"seq":18,"lat":41.866394,"lon":-87.613888,"type":"W","pdist":0},{"seq":19,"lat":41.866366,"lon":-87.61402,"type":"W","pdist":0},{"seq":20,"lat":41.866258,"lon":-87.614181,"type":"W","pdist":0},{"seq":21,"lat":41.866114,"lon":-87.614216,"type":"W","pdist":0},{"seq":22,"lat":41.865721,"lon":-87.614108,"type":"W","pdist":0},{"seq":23,"lat":41.865051,"lon":-87.61413,"type":"W","pdist":0},{"seq":24,"lat":41.86502,"lon":-87.6147,"type":"W","pdist":0},{"seq":25,"lat":41.86502,"lon":-87.61491,"type":"W","pdist":0},{"seq":26,"lat":41.865101000001,"lon":-87.614909999998,"type":"S","stopId":"15426","stopName":"Soldier Field & Field Museum","pdist":2694},{"seq":27,"lat":41.86502,"lon":-87.61491,"type":"W","pdist":0},{"seq":28,"lat":41.86502,"lon":-87.61555,"type":"W","pdist":0},{"seq":29,"lat":41.865,"lon":-87.61704,"type":"W","pdist":0},{"seq":30,"lat":41.865,"lon":-87.61819,"type":"W","pdist":0},{"seq":31,"lat":41.86497,"lon":-87.61899,"type":"W","pdist":0},{"seq":32,"lat":41.86498,"lon":-87.61918,"type":"W","pdist":0},{"seq":33,"lat":41.86497,"lon":-87.61929,"type":"W","pdist":0},{"seq":34,"lat":41.86497,"lon":-87.6194,"type":"W","pdist":0},{"seq":35,"lat":41.86515,"lon":-87.61955,"type":"W","pdist":0},{"seq":36,"lat":41.86758,"lon":-87.6203,"type":"W","pdist":0},{"seq":37,"lat":41.86759,"lon":-87.62168,"type":"W","pdist":0},{"seq":38,"lat":41.86751,"lon":-87.62343,"type":"W","pdist":0},{"seq":39,"lat":41.86751,"lon":-87.62387,"type":"W","pdist":0},{"seq":40,"lat":41.8675,"lon":-87.62406,"type":"W","pdist":0},{"seq":41,"lat":41.8675,"lon":-87.6242,"type":"W","pdist":0},{"seq":42,"lat":41.86749,"lon":-87.62484,"type":"W","pdist":0},{"seq":43,"lat":41.867518,"lon":-87.624836000001,"type":"S","stopId":"17084","stopName":"Roosevelt & Michigan","pdist":6137},{"seq":44,"lat":41.86749,"lon":-87.62483,"type":"W","pdist":0},{"seq":45,"lat":41.86748,"lon":-87.62499,"type":"W","pdist":0},{"seq":46,"lat":41.86748,"lon":-87.626298,"type":"W","pdist":0},{"seq":47,"lat":41.86748,"lon":-87.62669,"type":"W","pdist":0},{"seq":48,"lat":41.867547,"lon":-87.626693,"type":"S","stopId":"16140","stopName":"Roosevelt Orange/Red/Green Line Station","pdist":6643},{"seq":49,"lat":41.86747,"lon":-87.62669,"type":"W","pdist":0},{"seq":50,"lat":41.86749,"lon":-87.62737,"type":"W","pdist":0},{"seq":51,"lat":41.868958,"lon":-87.627387,"type":"W","pdist":0},{"seq":52,"lat":41.869098000001,"lon":-87.627372,"type":"S","stopId":"2354","stopName":"State & 11th Street","pdist":7415},{"seq":53,"lat":41.8691,"lon":-87.62741,"type":"W","pdist":0},{"seq":54,"lat":41.8704,"lon":-87.62743,"type":"W","pdist":0},{"seq":55,"lat":41.8704,"lon":-87.627354999998,"type":"S","stopId":"2355","stopName":"State & 9th Street","pdist":7890},{"seq":56,"lat":41.8704,"lon":-87.62743,"type":"W","pdist":0},{"seq":57,"lat":41.87298,"lon":-87.62748,"type":"W","pdist":0},{"seq":58,"lat":41.872978000001,"lon":-87.627423999998,"type":"S","stopId":"2357","stopName":"State & Balbo","pdist":8832},{"seq":59,"lat":41.87298,"lon":-87.62748,"type":"W","pdist":0},{"seq":60,"lat":41.874465,"lon":-87.627565,"type":"W","pdist":0},{"seq":61,"lat":41.87489,"lon":-87.62761,"type":"W","pdist":0},{"seq":62,"lat":41.874888,"lon":-87.627526999999,"type":"S","stopId":"15052","stopName":"State & Harrison/Ida B Wells Drive","pdist":9531},{"seq":63,"lat":41.87489,"lon":-87.62761,"type":"W","pdist":0},{"seq":64,"lat":41.87626,"lon":-87.62763,"type":"W","pdist":0},{"seq":65,"lat":41.87634,"lon":-87.62758,"type":"W","pdist":0},{"seq":66,"lat":41.87682,"lon":-87.62759,"type":"W","pdist":0},{"seq":67,"lat":41.876833999999,"lon":-87.627577000001,"type":"S","stopId":"1113","stopName":"State & Van Buren","pdist":10238},{"seq":68,"lat":41.878808,"lon":-87.627623,"type":"W","pdist":0},{"seq":69,"lat":41.879449,"lon":-87.627719,"type":"W","pdist":0},{"seq":70,"lat":41.87948,"lon":-87.62785,"type":"W","pdist":0},{"seq":71,"lat":41.87947,"lon":-87.62796,"type":"W","pdist":0},{"seq":72,"lat":41.87947,"lon":-87.62809,"type":"W","pdist":0},{"seq":73,"lat":41.879491,"lon":-87.628093000001,"type":"S","stopId":"4732","stopName":"Adams & State","pdist":11299},{"seq":74,"lat":41.87947,"lon":-87.62809,"type":"W","pdist":0},{"seq":75,"lat":41.87947,"lon":-87.6283,"type":"W","pdist":0},{"seq":76,"lat":41.87944,"lon":-87.63005,"type":"W","pdist":0},{"seq":77,"lat":41.87944,"lon":-87.63041,"type":"W","pdist":0},{"seq":78,"lat":41.87943,"lon":-87.6308,"type":"W","pdist":0},{"seq":79,"lat":41.87943,"lon":-87.63108,"type":"W","pdist":0},{"seq":80,"lat":41.879457,"lon":-87.631083,"type":"S","stopId":"17046","stopName":"Adams & Clark","pdist":12111},{"seq":81,"lat":41.87943,"lon":-87.63108,"type":"W","pdist":0},{"seq":82,"lat":41.87943,"lon":-87.63129,"type":"W","pdist":0},{"seq":83,"lat":41.87942,"lon":-87.63149,"type":"W","pdist":0},{"seq":84,"lat":41.87942,"lon":-87.63161,"type":"W","pdist":0},{"seq":85,"lat":41.87941,"lon":-87.63175,"type":"W","pdist":0},{"seq":86,"lat":41.87942,"lon":-87.6323,"type":"W","pdist":0},{"seq":87,"lat":41.87941,"lon":-87.63272,"type":"W","pdist":0},{"seq":88,"lat":41.87941,"lon":-87.63304,"type":"W","pdist":0},{"seq":89,"lat":41.8794,"lon":-87.6334,"type":"W","pdist":0},{"seq":90,"lat":41.8794,"lon":-87.63359,"type":"W","pdist":0},{"seq":91,"lat":41.87938,"lon":-87.63406,"type":"W","pdist":0},{"seq":92,"lat":41.87938,"lon":-87.63424,"type":"W","pdist":0},{"seq":93,"lat":41.879438999999,"lon":-87.634240999998,"type":"S","stopId":"80","stopName":"Adams & Wells","pdist":12970},{"seq":94,"lat":41.87938,"lon":-87.63424,"type":"W","pdist":0},{"seq":95,"lat":41.87938,"lon":-87.63537,"type":"W","pdist":0},{"seq":96,"lat":41.87936,"lon":-87.63622,"type":"W","pdist":0},{"seq":97,"lat":41.87936,"lon":-87.63653,"type":"W","pdist":0},{"seq":98,"lat":41.879421,"lon":-87.636526999999,"type":"S","stopId":"1108","stopName":"Adams & S. Wacker","pdist":13592},{"seq":99,"lat":41.87936,"lon":-87.63653,"type":"W","pdist":0},{"seq":100,"lat":41.87936,"lon":-87.63671,"type":"W","pdist":0},{"seq":101,"lat":41.87935,"lon":-87.63696,"type":"W","pdist":0},{"seq":102,"lat":41.87935,"lon":-87.63753,"type":"W","pdist":0},{"seq":103,"lat":41.87934,"lon":-87.63798,"type":"W","pdist":0},{"seq":104,"lat":41.87934,"lon":-87.6384,"type":"W","pdist":0},{"seq":105,"lat":41.87933,"lon":-87.63857,"type":"W","pdist":0},{"seq":106,"lat":41.87933,"lon":-87.63904,"type":"W","pdist":0},{"seq":107,"lat":41.87932,"lon":-87.63928,"type":"W","pdist":0},{"seq":108,"lat":41.87932,"lon":-87.63936,"type":"W","pdist":0},{"seq":109,"lat":41.879387,"lon":-87.639358999998,"type":"S","stopId":"12713","stopName":"Adams & Canal","pdist":14361},{"seq":110,"lat":41.87932,"lon":-87.63936,"type":"W","pdist":0},{"seq":111,"lat":41.87932,"lon":-87.6396,"type":"W","pdist":0},{"seq":112,"lat":41.87932,"lon":-87.64003,"type":"W","pdist":0},{"seq":113,"lat":41.87931,"lon":-87.64027,"type":"W","pdist":0},{"seq":114,"lat":41.87931,"lon":-87.64078,"type":"W","pdist":0},{"seq":115,"lat":41.8793,"lon":-87.64112,"type":"W","pdist":0},{"seq":116,"lat":41.8793,"lon":-87.64167,"type":"W","pdist":0},{"seq":117,"lat":41.87929,"lon":-87.64239,"type":"W","pdist":0},{"seq":118,"lat":41.87929,"lon":-87.64258,"type":"W","pdist":0},{"seq":119,"lat":41.883,"lon":-87.6427,"type":"W","pdist":0},{"seq":120,"lat":41.883002999999,"lon":-87.642615000001,"type":"S","stopId":"5516","stopName":"Jefferson & Washington","pdist":16590},{"seq":121,"lat":41.883,"lon":-87.6427,"type":"W","pdist":0},{"seq":122,"lat":41.88571,"lon":-87.64278,"type":"W","pdist":0},{"seq":123,"lat":41.88571,"lon":-87.64132,"type":"W","pdist":0},{"seq":124,"lat":41.88351,"lon":-87.64125,"type":"W","pdist":0},{"seq":125,"lat":41.883348,"lon":-87.641336000001,"type":"S","stopId":"5023","stopName":"Clinton & Washington","pdist":18842}]}